LICENSE
README.md
pyproject.toml
setup.py
src/git_release_tag/__init__.py
src/git_release_tag/__main__.py
src/git_release_tag/click_parameter_types.py
src/git_release_tag/git.py
src/git_release_tag/logger.py
src/git_release_tag/release_info.py
src/git_release_tag.egg-info/PKG-INFO
src/git_release_tag.egg-info/SOURCES.txt
src/git_release_tag.egg-info/dependency_links.txt
src/git_release_tag.egg-info/entry_points.txt
src/git_release_tag.egg-info/not-zip-safe
src/git_release_tag.egg-info/requires.txt
src/git_release_tag.egg-info/top_level.txt
tests/test_bump.py
tests/test_initialize.py
tests/test_ordering.py